pytt_events/__init__.py
pytt_events/auth.py
pytt_events/context.py
pytt_events/event.py
pytt_events/properties.py
pytt_events/supported_events.py
pytt_events/tiktok_events_api.py
pytt_events/utils.py
pytt_events/tests/__init__.py
pytt_events/tests/conftest.py
pytt_events/tests/test_event.py
pytt_events/tests/test_tiktok_post_events.py
pytt_events_api-0.1.10.dist-info/LICENSE
pytt_events_api-0.1.10.dist-info/METADATA
pytt_events_api-0.1.10.dist-info/WHEEL
pytt_events_api-0.1.10.dist-info/top_level.txt
pytt_events_api-0.1.10.dist-info/RECORD
