Metadata-Version: 2.1
Name: pytt-events-api
Version: 0.1.10
Summary: Python wrapper for the TikTok Events API
Home-page: UNKNOWN
Author: Victor Valar
Author-email: <valar@victorvalar.me>
License: LICENSE.txt
Keywords: python,tiktok,events,api,tiktok ads,tiktok events api
Platform: UNKNOWN
Classifier: Development Status :: 4 - Beta
Classifier: Intended Audience :: Developers
Classifier: Programming Language :: Python :: 3
Classifier: Operating System :: Unix
Classifier: Operating System :: MacOS :: MacOS X
Classifier: Operating System :: Microsoft :: Windows
License-File: LICENSE
Requires-Dist: email-validator
Requires-Dist: ipaddress
Requires-Dist: phonenumbers
Requires-Dist: pydantic (==1.10.4)
Requires-Dist: pydantic[dotenv]
Requires-Dist: requests
